KnowledgeFeed/__init__.py
KnowledgeFeed/main.py
KnowledgeFeed/test.py
knowledgefeed-0.1.0.dist-info/LICENSE
knowledgefeed-0.1.0.dist-info/METADATA
knowledgefeed-0.1.0.dist-info/WHEEL
knowledgefeed-0.1.0.dist-info/top_level.txt
knowledgefeed-0.1.0.dist-info/RECORD
